wtf_polyglot/__init__.py
wtf_polyglot/fields.py
wtf_polyglot/form.py
wtf_polyglot/meta.py
wtf_polyglot/widgets.py
wtforms_polyglot-0.4.0.dist-info/LICENSE
wtforms_polyglot-0.4.0.dist-info/METADATA
wtforms_polyglot-0.4.0.dist-info/WHEEL
wtforms_polyglot-0.4.0.dist-info/RECORD
